st_card_search_component/__init__.py
st_card_search_component/frontend/build/asset-manifest.json
st_card_search_component/frontend/build/bootstrap.min.css
st_card_search_component/frontend/build/index.html
st_card_search_component/frontend/build/precache-manifest.aa7fc790e856c6fd4d046960beb97ecc.js
st_card_search_component/frontend/build/service-worker.js
st_card_search_component/frontend/build/static/js/2.78f63e51.chunk.js
st_card_search_component/frontend/build/static/js/2.78f63e51.chunk.js.LICENSE.txt
st_card_search_component/frontend/build/static/js/2.78f63e51.chunk.js.map
st_card_search_component/frontend/build/static/js/main.a1f3ca45.chunk.js
st_card_search_component/frontend/build/static/js/main.a1f3ca45.chunk.js.map
st_card_search_component/frontend/build/static/js/runtime-main.44d30fc2.js
st_card_search_component/frontend/build/static/js/runtime-main.44d30fc2.js.map
st_card_search_component-0.0.3.dist-info/LICENSE
st_card_search_component-0.0.3.dist-info/METADATA
st_card_search_component-0.0.3.dist-info/WHEEL
st_card_search_component-0.0.3.dist-info/top_level.txt
st_card_search_component-0.0.3.dist-info/RECORD
