Metadata-Version: 2.1
Name: st-card-search-component
Version: 0.0.3
Summary: UNKNOWN
Home-page: 
Author: 
Author-email: 
License: UNKNOWN
Platform: UNKNOWN
Requires-Python: >=3.6
License-File: LICENSE
Requires-Dist: streamlit (>=0.63)
